{
    "title": "RSS Feed Title",
    "link": "https://example.com",
    "description": "RSS Feed Description",
    "lastBuildDate": "2024-09-28T07:09:14.052118",
    "items": [
        {
            "title": "Kross standalone net profit declines 4.25% in the June 2024 quarter",
            "link": "https://www.business-standard.com/markets/capital-market-news/kross-standalone-net-profit-declines-4-25-in-the-june-2024-quarter-124092800104_1.html",
            "description": "",
            "pubDate": "2024-09-28T03:41:04.093127"
        },
        {
            "title": "Jamna Auto Industries consolidated net profit rises 1.73% in the June 2024 quarter",
            "link": "https://www.business-standard.com/markets/capital-market-news/jamna-auto-industries-consolidated-net-profit-rises-1-73-in-the-june-2024-quarter-124092800103_1.html",
            "description": "",
            "pubDate": "2024-09-28T03:41:04.093244"
        },
        {
            "title": "IDFC First Bank fixes record date for Scheme of Amalgamation",
            "link": "https://www.business-standard.com/markets/capital-market-news/idfc-first-bank-fixes-record-date-for-scheme-of-amalgamation-124092800197_1.html",
            "description": "",
            "pubDate": "2024-09-28T05:32:27.901682"
        },
        {
            "title": "Avantel bags order worth Rs 44 cr from Larsen & Toubro",
            "link": "https://www.business-standard.com/markets/capital-market-news/avantel-bags-order-worth-rs-44-cr-from-larsen-toubro-124092800192_1.html",
            "description": "",
            "pubDate": "2024-09-28T05:32:27.901800"
        },
        {
            "title": "Bajel bags its maiden order in the data center segment",
            "link": "https://www.business-standard.com/markets/capital-market-news/bajel-bags-its-maiden-order-in-the-data-center-segment-124092800212_1.html",
            "description": "",
            "pubDate": "2024-09-28T05:41:41.203126"
        },
        {
            "title": "Oriental Rail Infra bags order worth Rs 1.79 cr",
            "link": "https://www.business-standard.com/markets/capital-market-news/oriental-rail-infra-bags-order-worth-rs-1-79-cr-124092800211_1.html",
            "description": "",
            "pubDate": "2024-09-28T05:41:41.203231"
        },
        {
            "title": "Ola Electric plans to double its service network by Dec'24",
            "link": "https://www.business-standard.com/markets/capital-market-news/ola-electric-plans-to-double-its-service-network-by-dec-24-124092800222_1.html",
            "description": "",
            "pubDate": "2024-09-28T05:49:36.561444"
        },
        {
            "title": "Saksoft acquires Bangalore-based Salesforce Summit Partner 'Ceptes Software'",
            "link": "https://www.business-standard.com/markets/capital-market-news/saksoft-acquires-bangalore-based-salesforce-summit-partner-ceptes-software-124092800243_1.html",
            "description": "",
            "pubDate": "2024-09-28T06:38:39.507300"
        },
        {
            "title": "Bajel Projects wins first data centre order",
            "link": "https://www.business-standard.com/markets/capital-market-news/bajel-projects-wins-first-data-centre-order-124092800273_1.html",
            "description": "",
            "pubDate": "2024-09-28T07:09:13.285964"
        }
    ]
}