{
    "title": "RSS Feed Title",
    "link": "https://example.com",
    "description": "RSS Feed Description",
    "lastBuildDate": "2024-10-15T06:24:23.568915",
    "items": [
        {
            "title": "Market Today: RIL, HCL Q2, Hyundai Motor IPO, Garuda Construction listing",
            "link": "https://www.business-standard.com/markets/news/market-today-ril-hcl-q2-nos-s-p-500-dow-hit-record-hyundai-motor-ipo-124101500054_1.html",
            "description": "At 6:33 AM, GIFT Nifty Futures were trading 30 points higher at 25,251, suggesting a higher start for Indian markets.",
            "pubDate": "2024-10-15T02:06:51.660465"
        },
        {
            "title": "Nifty Fin Svcs, PSU Bank rangebound; time to be cautious? What analysts say",
            "link": "https://www.business-standard.com/markets/news/nifty-fin-svcs-psu-bank-rangebound-time-to-be-cautious-what-analysts-say-124101500057_1.html",
            "description": "The Nifty Financial Services Index is currently trading within a well-defined range of 23,900 to 23,100. This range-bound pattern indicates consolidation in the market",
            "pubDate": "2024-10-15T02:06:51.660580"
        },
        {
            "title": "Stocks To Watch: RIL, HCLTech, L&T, Adani Power, Atul Auto, SpiceJet",
            "link": "https://www.business-standard.com/markets/news/stocks-to-watch-ril-hcltech-l-t-adani-power-atul-auto-spicejet-124101500053_1.html",
            "description": "Stock Market Today: RIL reported a 4.8 per cent year-on-year decline in consolidated profit for Q2 FY25, totaling Rs 16,563 crore, and missing analyst expectations.",
            "pubDate": "2024-10-15T02:06:51.660677"
        },
        {
            "title": "Stock Market LIVE Updates: India markets likely to open higher, signals GIFT Nifty; Nikkei up 1.6%",
            "link": "https://www.business-standard.com/markets/news/stock-market-live-updates-today-sensex-nifty-nse-bse-live-blog-oct-15-ril-hcl-q2-results-hyundai-ipo-124101500065_1.html",
            "description": "Stock Market Today: GIFT Nifty futures, trading marginally ahead of Nifty futures' last close, indicated a slight upside at open for India markets on Tuesday.",
            "pubDate": "2024-10-15T02:56:58.991238"
        },
        {
            "title": "Hyundai Motor India IPO opens: GMP shows slight uptick; Should you apply?",
            "link": "https://www.business-standard.com/markets/news/hyundai-motor-india-ipo-opens-gmp-shows-slight-uptick-should-you-apply-124101500090_1.html",
            "description": "Hyundai Motor India IPO opens for public subscription from October 15, 2024, to October 17, 2024. Check here for key details: Price Band, Lot Size, GMP, Allotment Date, Listing Date, and more",
            "pubDate": "2024-10-15T03:40:28.607862"
        },
        {
            "title": "Pivot point for Nifty 50 index moves higher to 25,150, suggests F&O data",
            "link": "https://www.business-standard.com/markets/news/pivot-point-for-nifty-50-index-moves-higher-to-25-150-suggests-f-o-data-124101500109_1.html",
            "description": "Derivatives market update Oct 15: In case of Bank Nifty the max pain is seen at 51,800; with the PCR rising to 1 - tilt towards a bullish bias is observed, says SAMCO Securities analyst.",
            "pubDate": "2024-10-15T03:50:30.361156"
        },
        {
            "title": "Lykka Labs shares rally 7% on CDSCO nod for diabetic neuropathy pain drug",
            "link": "https://www.business-standard.com/markets/news/lykka-labs-shares-rally-7-on-cdsco-nod-for-diabetic-neuropathy-pain-drug-124101500160_1.html",
            "description": "Lyka Labs shares rose as the company announced that it has received the CDSCO approval for manufacturing & marketing of of Pregabalin Gel 8% w/w for use in patients with Diabetic Neuropathic Pain.",
            "pubDate": "2024-10-15T04:36:48.861128"
        },
        {
            "title": "Brokerages bullish on HCL Tech post Q2FY25 outperformance, raise EPS target",
            "link": "https://www.business-standard.com/markets/news/hcl-tech-share-price-brokerages-bullish-on-hcl-tech-post-q2fy25-outperformance-raise-eps-target-124101500138_1.html",
            "description": "Shares of HCL Tech hit their lifetime high at Rs 1,882, rising by 1.40 per cent on the BSE in Tuesday's intraday deals after the company delivered solid performance in its quarter two results",
            "pubDate": "2024-10-15T04:36:48.861290"
        },
        {
            "title": "Garuda Construction shares list at 10% premium defying IPO GMP trend",
            "link": "https://www.business-standard.com/markets/news/garuda-construction-shares-list-at-10-premium-defying-ipo-gmp-trend-124101500156_1.html",
            "description": "Ahead of the listing, the grey market premium for Garuda Construction's IPO turned flat, signaling a subdued debut for the company's shares",
            "pubDate": "2024-10-15T04:36:48.861362"
        },
        {
            "title": "J Kumar Infra up 3% on Rs 298-cr work order from Pune Municipal Corporation",
            "link": "https://www.business-standard.com/markets/news/j-kumar-infra-up-3-on-rs-298-cr-work-order-from-pune-municipal-corporation-124101500193_1.html",
            "description": "The rise in J Kumar Infra share price came after the company announced that it has secured an order worth Rs 297.83 crore from Pune Municipal Corporation (PMC).",
            "pubDate": "2024-10-15T05:10:39.319762"
        },
        {
            "title": "Network18, TV18 rally on RIL plans to close merger with Disney India in Q3",
            "link": "https://www.business-standard.com/markets/news/ril-s-media-co-stocks-rally-after-update-on-merger-with-disney-india-124101500190_1.html",
            "description": "Shares of media majors Network 18 Media and Investments and TV18 Broadcast soared up to over 9 per cent in intraday trade on Tuesday on the NSE",
            "pubDate": "2024-10-15T05:10:39.319903"
        },
        {
            "title": "How to trade RIL stock post Q2 results? All eyes on this long-term MA",
            "link": "https://www.business-standard.com/markets/news/how-to-trade-ril-stock-post-q2-results-all-eyes-on-this-long-term-ma-124101500244_1.html",
            "description": "As traders await bonus share record date announcement; technical chart shows that Reliance stock has strong support at Rs 2,640 its 20-MMA - a key moving average the stock has held since June 2023.",
            "pubDate": "2024-10-15T05:31:16.159972"
        },
        {
            "title": "Angel One soars 9% post Q2 results, Motilal Oswal Financial hits new high",
            "link": "https://www.business-standard.com/markets/news/angel-one-soars-9-post-q2-results-motilal-oswal-financial-hits-new-high-124101500169_1.html",
            "description": "Angel One reported a healthy 44 per cent year-on-year jump in its consolidated profit after tax at Rs 423.4 crore, in the September 2024 quarter.",
            "pubDate": "2024-10-15T05:31:16.160046"
        },
        {
            "title": "Exxaro Tiles share rise 4% on 1:10 stock-split announcement; details here",
            "link": "https://www.business-standard.com/markets/news/exxaro-tiles-share-rise-4-on-1-10-stock-split-announcement-details-here-124101500279_1.html",
            "description": "The surge in Exxaro Tiles share price came after the company announced that its board has approved a 1:10 stock split.",
            "pubDate": "2024-10-15T05:42:47.438477"
        },
        {
            "title": "Reliance results: Weak O2C, Retail biz to keep shares sideways, say experts",
            "link": "https://www.business-standard.com/markets/news/reliance-results-weak-o2c-retail-biz-to-keep-shares-sideways-say-experts-124101500282_1.html",
            "description": "RIL share price: Some brokerages have also cut Reliance Industries (RIL) share price targets, factoring-in the sluggishness seen in oil-to-chemical (O2C) and retail verticals",
            "pubDate": "2024-10-15T05:42:47.438558"
        },
        {
            "title": "VA Tech Wabag hits record high after receiving order worth Rs 1,000 cr",
            "link": "https://www.business-standard.com/markets/news/va-tech-wabag-hits-record-high-after-receiving-order-worth-rs-1-000-cr-124101500283_1.html",
            "description": "Shares of VA Tech Wabag reached their all time high at Rs 1,743.85 a piece on the BSE, rising 4.3 per cent in Tuesday's intraday deals",
            "pubDate": "2024-10-15T05:42:47.438635"
        },
        {
            "title": "This stock has zoomed 900% over its issue price in less than 2 years",
            "link": "https://www.business-standard.com/markets/news/this-stock-has-zoomed-900-over-its-issue-price-in-less-than-2-years-124101500296_1.html",
            "description": "Kaynes Technology share price hit a record high of Rs 5,876.60, up 3% on the BSE in Tuesday's intraday trade. Kaynes shares have zoomed 125% in the past five months on a healthy business outlook",
            "pubDate": "2024-10-15T06:24:20.634177"
        },
        {
            "title": "Axis Bank Q2 results preview: Analysts see modest profit growth, weak NIM",
            "link": "https://www.business-standard.com/markets/news/axis-bank-q2-results-preview-analysts-see-modest-profit-growth-weak-nim-124101500325_1.html",
            "description": "Axis Bank Q2 results: Domestic brokerage Motilal Oswal Financial estimates Axis Bank's Q2 profit after tax at Rs 6,630 crore, up 13 per cent Y-o-Y",
            "pubDate": "2024-10-15T06:24:20.634262"
        },
        {
            "title": "Rs 142-crore order win boosts TD Power Systems share price by 6%",
            "link": "https://www.business-standard.com/markets/news/rs-142-crore-order-win-boosts-td-power-systems-share-price-by-6-124101500327_1.html",
            "description": "TD Power Systems share price jumped after the company announced that it has secured an order worth Rs 142 crore from two major international gas engine Original Equipment Manufacturers (OEMs)",
            "pubDate": "2024-10-15T06:24:20.634339"
        },
        {
            "title": "Wipro Q2FY25 preview: Revenue may fall up to 3% YoY; margin, guidance eyed",
            "link": "https://www.business-standard.com/markets/news/wipro-q2fy25-preview-revenue-may-fall-up-to-3-yoy-margin-guidance-eyed-124101500117_1.html",
            "description": "Overall, the sentiment remains cautiously optimistic for Wipro ahead of results, with key focus areas including large-deal pipelines and consulting growth.",
            "pubDate": "2024-10-15T06:24:20.634441"
        }
    ]
}