{
    "title": "RSS Feed Title",
    "link": "https://example.com",
    "description": "RSS Feed Description",
    "lastBuildDate": "2024-10-02T14:13:22.022388",
    "items": [
        {
            "title": "Trend turnover, MF plan funds around 'quality' theme instead of 'value'",
            "link": "https://www.business-standard.com/markets/mutual-fund/trend-turnover-mf-plan-funds-around-quality-theme-instead-of-value-124100200731_1.html",
            "description": "WhiteOak Capital and ICICI Prudential have sought regulatory approval for a first-of-its-kind active quality fund",
            "pubDate": "2024-10-02T14:13:21.373057"
        }
    ]
}