{
    "title": "RSS Feed Title",
    "link": "https://example.com",
    "description": "RSS Feed Description",
    "lastBuildDate": "2024-09-03T06:30:51.829864",
    "items": [
        {
            "title": "Premier Energies shares double investors money with bumper debut on bourses",
            "link": "https://www.business-standard.com/markets/news/premier-energies-shares-double-investors-money-with-bumper-debut-on-bourses-124090300159_1.html",
            "description": "Premier Energies IPO listing today: The company's shares listed at Rs 991 on the BSE, reflecting a whopping 120.22 per cent premium over the upper end of its issue price of Rs 450",
            "pubDate": "2024-09-03T04:48:46.040574"
        },
        {
            "title": "Last Chance! Baazar Style IPO ends today: should you bid? Check GMP & more",
            "link": "https://www.business-standard.com/markets/news/last-chance-baazar-style-ipo-ends-today-should-you-bid-check-gmp-more-124090300320_1.html",
            "description": "The three-day subscription window to bid for the Baazar Style Retail IPO, which opened on Friday, August 30, 2024, is set to conclude today",
            "pubDate": "2024-09-03T06:30:51.254985"
        }
    ]
}