{
    "title": "RSS Feed Title",
    "link": "https://example.com",
    "description": "RSS Feed Description",
    "lastBuildDate": "2024-09-26T11:58:52.279171",
    "items": [
        {
            "title": "Ajit Mishra from Religare Broking suggests buying these three stocks today",
            "link": "https://www.business-standard.com/markets/news/ajit-mishra-from-religare-broking-suggests-buying-these-three-stocks-today-124092600073_1.html",
            "description": "NTPC is displaying a strong uptrend, characterised by a steady pattern of higher highs and higher lows.",
            "pubDate": "2024-09-26T01:41:28.770270"
        },
        {
            "title": "Nifty IT shows bearish trend, Nifty Auto overbought; trading strategy here",
            "link": "https://www.business-standard.com/markets/news/nifty-it-shows-bearish-trend-nifty-auto-overbought-trading-strategy-here-124092600072_1.html",
            "description": "The Nifty Auto Index appears overbought on the near-term charts, indicating a potential pullback in the coming sessions, likely after the monthly expiry.",
            "pubDate": "2024-09-26T01:41:28.770357"
        },
        {
            "title": "Stock Market LIVE Updates: India markets set for higher open tracking global cues; Vedanta, BOI eyed",
            "link": "https://www.business-standard.com/markets/news/stock-market-live-updates-today-sensex-nifty-nse-bse-vedanta-hdfc-bank-kalana-ipo-124092600094_1.html",
            "description": "Stock Market LIVE Updates: Markets in India were likely to start on a positive note on Thursday, following the surge in markets in the Asia-Pacific region.",
            "pubDate": "2024-09-26T02:40:26.946758"
        },
        {
            "title": "Stocks To Watch: SBI, Vedanta, HDFC Bank, Piramal Pharma, Bank of India",
            "link": "https://www.business-standard.com/markets/news/stocks-to-watch-sbi-vedanta-hdfc-bank-piramal-pharma-bank-of-india-124092600085_1.html",
            "description": "Stocks to watch: Piramal Pharma aims to double its revenue to $2 billion by FY30, while tripling its Ebitda, said company Chairperson Nandini Piramal.",
            "pubDate": "2024-09-26T02:40:26.946949"
        },
        {
            "title": "Stock Market Today: Nifty expiry, Israel conflict & Kalana Ispat IPO debut",
            "link": "https://www.business-standard.com/markets/news/stock-market-today-nifty-expiry-israel-conflict-kalana-ispat-ipo-debut-124092600083_1.html",
            "description": "The uptrend was signalled by GIFT Nifty futures that were trading about 50 points higher than Nifty futures' last close, at 26,047.50, around 7:30 AM.",
            "pubDate": "2024-09-26T02:40:26.947024"
        },
        {
            "title": "Dividend, bonus, stock-split: These 4 companies will trade ex-date tomorrow",
            "link": "https://www.business-standard.com/markets/news/dividend-bonus-stock-split-these-4-companies-will-trade-ex-date-tomorrow-124092600104_1.html",
            "description": "Here is the full list of stocks that will trade ex-dat e tomorrow for purpose of several corporation actions that these companies have announced",
            "pubDate": "2024-09-26T03:30:29.550335"
        },
        {
            "title": "Manba Finance IPO allotment today: Check status, GMP, likely listing price",
            "link": "https://www.business-standard.com/markets/news/manba-finance-ipo-allotment-today-check-status-gmp-likely-listing-price-124092600135_1.html",
            "description": "Once the allotment is finalized, investors can check the allotment status of the Manba Finance IPO by visiting the official websites of either BSE, NSE, or Link Intime",
            "pubDate": "2024-09-26T03:51:36.605421"
        },
        {
            "title": "PB Fintech shares down 5% after co plans foray into healthcare space",
            "link": "https://www.business-standard.com/markets/news/pb-fintech-shares-down-5-after-co-plans-foray-into-healthcare-space-124092600160_1.html",
            "description": "The fall in PB Fintech share price comes after the company indicated that it may foray into the healthcare space.",
            "pubDate": "2024-09-26T04:24:30.780174"
        },
        {
            "title": "Hero MotoCorp share price falls 3% in firm market; UBS maintains 'Sell'",
            "link": "https://www.business-standard.com/markets/news/hero-motocorp-share-price-falls-3-in-firm-market-ubs-maintains-sell-124092600189_1.html",
            "description": "Hero MotoCorp share price today declined 2.7 per cent in the intraday trade on Thursday. Read why global brokerage UBS sees nearly 45 per cent downside in the two-wheeler company's stock price",
            "pubDate": "2024-09-26T04:56:13.022422"
        },
        {
            "title": "Diffusion Engineers IPO opens today: GMP up 48%; is it worth your money?",
            "link": "https://www.business-standard.com/markets/news/diffusion-engineers-ipo-opens-today-gmp-up-48-is-it-worth-your-money-124092600231_1.html",
            "description": "The unlisted shares of Diffusion Engineers were trading at a premium of Rs 80, or 48 per cent against the upper end of the IPO price, reflecting positive market sentiments for the public issue",
            "pubDate": "2024-09-26T05:13:16.653936"
        },
        {
            "title": "Five-star Business Finance Block Deal: 28 mn shares change hands, stk up 4%",
            "link": "https://www.business-standard.com/markets/news/five-star-business-finance-block-deal-28-mn-shares-change-hands-stk-up-4-124092600237_1.html",
            "description": "The surge in Five-Star Business Finance share price came after 28.1 million (or 2.81 crore) shares changed hands via a block deal.",
            "pubDate": "2024-09-26T05:13:16.654028"
        },
        {
            "title": "Indian shares hit record highs helped by gains in IT and consumer firms",
            "link": "https://www.business-standard.com/markets/news/indian-shares-hit-record-highs-helped-by-gains-in-it-and-consumer-firms-124092600161_1.html",
            "description": "The consumer goods index was up 0.4 per cent and was among the top gainers of the 13 major sub-indexes",
            "pubDate": "2024-09-26T05:13:16.654104"
        },
        {
            "title": "Indian bond yields may partly reverse fall as US peers move higher",
            "link": "https://www.business-standard.com/markets/news/indian-bond-yields-may-partly-reverse-fall-as-us-peers-move-higher-124092600216_1.html",
            "description": "US bond yields rose, as traders booked profits after a recent fall, and as yields witnessed a floor. However, the possibility that the Fed could do another outsized rate cut remain intact",
            "pubDate": "2024-09-26T05:13:16.654278"
        },
        {
            "title": "This Tata Group stock has beat Sensex for a decade, surged 1,154% in 4 yrs",
            "link": "https://www.business-standard.com/markets/news/this-tata-group-stock-beat-sensex-for-a-decade-zoomed-160-thus-far-in-2024-124092600239_1.html",
            "description": "Trent shares hit a new high of Rs 7,939.90, following a 4% rally on the NSE after Citi initiated coverage on the stock with a 'Buy' rating and a target price of Rs 9,250.",
            "pubDate": "2024-09-26T05:58:00.920209"
        },
        {
            "title": "India's private debt market to surpass $18 billion in AUM by year-end",
            "link": "https://www.business-standard.com/markets/news/india-s-private-debt-market-to-surpass-18-billion-in-aum-by-year-end-124092600296_1.html",
            "description": "The report highlights that India-focused private debt AUM grew from under $14 billion at the end of 2022 to nearly $18 billion a year later",
            "pubDate": "2024-09-26T05:58:00.920372"
        },
        {
            "title": "Easy Trip Rebounds: Share gains 7% after hitting 52-wk low in last session",
            "link": "https://www.business-standard.com/markets/news/easy-trip-rebounds-share-gains-7-after-hitting-52-wk-low-in-prev-session-124092600317_1.html",
            "description": "Easy Trip stock rebound followed a major drop of up to 8 per cent the previous day amid multiple block deals. The drop, meanwhile, led to a fresh 52-week low for the stock.",
            "pubDate": "2024-09-26T06:24:02.872535"
        },
        {
            "title": "Intellect Design's biz unit launches eMACH.ai Retail 6DX; share price up 4%",
            "link": "https://www.business-standard.com/markets/news/intellect-design-s-biz-unit-launches-emach-ai-retail-6dx-share-price-up-4-124092600359_1.html",
            "description": "Intellect Design's share price surged after the company's business unit, Intellect Digital Technology for Commerce (iDTC), launched eMACH.ai Retail 6DX, tailored for the Middle Eastern market.",
            "pubDate": "2024-09-26T06:42:45.815488"
        },
        {
            "title": "Vedanta shareholders to rejoice: Company lines up for 4th dividend for FY25",
            "link": "https://www.business-standard.com/markets/news/vedanta-shareholders-to-rejoice-company-lines-up-for-4th-dividend-for-fy25-124092600355_1.html",
            "description": "The uptick in Vedanta's stock was fueled by the company's plan to declare a fourth interim dividend for FY25",
            "pubDate": "2024-09-26T06:42:45.815573"
        },
        {
            "title": "Newgen Software surges 19% on heavy volumes; zooms 42% in two weeks",
            "link": "https://www.business-standard.com/markets/news/newgen-software-surges-19-on-heavy-volumes-zooms-42-in-two-weeks-124092600333_1.html",
            "description": "A combined 2.42 million equity shares, representing 1.73 per cent of the total equity of the company, had changed hands on the NSE and BSE till 11:21 AM.",
            "pubDate": "2024-09-26T06:51:44.669951"
        },
        {
            "title": "Zen Tech up 4% on launching remote-operated weapon & surveillance systems",
            "link": "https://www.business-standard.com/markets/news/zen-tech-up-4-on-launching-remote-operated-weapon-surveillance-systems-124092600455_1.html",
            "description": "The rise in Zen Technologies share price came after the company announced that it has launched remote-controlled weapon and surveillance systems to strengthen India's defence capabilities.",
            "pubDate": "2024-09-26T07:45:33.383338"
        },
        {
            "title": "Stock of this Z group company has zoomed over 3,300% so far in 2024",
            "link": "https://www.business-standard.com/markets/news/this-z-group-stock-price-has-zoomed-over-3300-thus-far-in-2024-124092600416_1.html",
            "description": "Marsons' shares hit a new high of Rs 267.55 in intra-day trade today, after having skyrocketed 3,352%, or nearly 35 times, from level of Rs 7.75 on December 29, 2023.",
            "pubDate": "2024-09-26T07:53:00.729101"
        },
        {
            "title": "Krsnaa Diagnostics climbs 4% on buying stake in Apulki Healthcare",
            "link": "https://www.business-standard.com/markets/news/krsnaa-diagnostics-climbs-4-on-buying-stake-in-apulki-healthcare-124092600481_1.html",
            "description": "The northward movement in the company's stock follows the announcement of a strategic investment in Apulki Healthcare (Apulki)",
            "pubDate": "2024-09-26T08:10:03.618680"
        },
        {
            "title": "Auto index hits record as MSIL surges 5%, M&M, Bajaj Auto hit life highs",
            "link": "https://www.business-standard.com/markets/news/auto-index-hits-record-high-msil-surges-5-m-m-bajaj-auto-hit-new-high-124092600522_1.html",
            "description": "Thus far in calendar year 2024, the BSE Auto index has surged 46 per cent, compared to the 18 per cent rally in BSE Sensex.",
            "pubDate": "2024-09-26T09:11:16.499204"
        },
        {
            "title": "Mitsubishi Pencil JV boosts Linc shares by 6%: details for investors",
            "link": "https://www.business-standard.com/markets/news/mitsubishi-pencil-jv-boosts-linc-shares-by-6-details-for-investors-124092600580_1.html",
            "description": "The joint venture taps into Mitsubishi's global writing instruments expertise and an annual turnover exceeding $500 million",
            "pubDate": "2024-09-26T09:29:34.977725"
        },
        {
            "title": "Mutual funds' search for debt fund alternatives reaches FoF space",
            "link": "https://www.business-standard.com/markets/news/mutual-funds-search-for-debt-fund-alternatives-reaches-fof-space-124092600704_1.html",
            "description": "HDFC, ABSL plan arbitrage-plus-debt FoFs to offer low-risk but tax-efficient products",
            "pubDate": "2024-09-26T11:58:51.576383"
        }
    ]
}