{
    "title": "RSS Feed Title",
    "link": "https://example.com",
    "description": "RSS Feed Description",
    "lastBuildDate": "2024-10-14T07:23:54.226328",
    "items": [
        {
            "title": "Hyundai Motor India IPO review: Worth investing? Brokerages' recommendation",
            "link": "https://www.business-standard.com/markets/news/hyundai-motor-india-ipo-review-worth-investing-brokerages-recommendation-124101400367_1.html",
            "description": "Hyundai Motor India IPO review: Valuation, GMP, brokerages views - Here's all you need to know before investing in the mega offering",
            "pubDate": "2024-10-14T07:23:53.240138"
        },
        {
            "title": "BlackRock, GIC, Capital Group to invest in Hyundai Motor India IPO",
            "link": "https://www.business-standard.com/markets/ipo/blackrock-gic-capital-group-to-invest-in-hyundai-motor-india-ipo-124101101125_1.html",
            "description": "Baillie Gifford and FMR are also looking to participate in the record-breaking offering in Mumbai, the people said, asking not to be identified as the information isn't public",
            "pubDate": "2024-10-14T07:23:53.240221"
        }
    ]
}