{
    "title": "RSS Feed Title",
    "link": "https://example.com",
    "description": "RSS Feed Description",
    "lastBuildDate": "2024-10-15T07:22:41.998214",
    "items": [
        {
            "title": "Hyundai Motor India IPO opens: GMP shows slight uptick; Should you apply?",
            "link": "https://www.business-standard.com/markets/news/hyundai-motor-india-ipo-opens-gmp-shows-slight-uptick-should-you-apply-124101500090_1.html",
            "description": "Hyundai Motor India IPO opens for public subscription from October 15, 2024, to October 17, 2024. Check here for key details: Price Band, Lot Size, GMP, Allotment Date, Listing Date, and more",
            "pubDate": "2024-10-15T03:40:25.909805"
        },
        {
            "title": "Waaree Energies IPO: 5 key things to know from RHP before bidding starts",
            "link": "https://www.business-standard.com/markets/news/waaree-energies-ipo-5-key-things-to-know-from-rhp-before-bidding-starts-124101500373_1.html",
            "description": "Having secured 'in-principle' approvals from the BSE, and National Stock Exchange (NSE) for the listing of its equity shares, Waaree Energies is all set for its market debut",
            "pubDate": "2024-10-15T07:22:41.247465"
        }
    ]
}