{
    "title": "RSS Feed Title",
    "link": "https://example.com",
    "description": "RSS Feed Description",
    "lastBuildDate": "2026-02-01T10:23:20.065308",
    "items": [
        {
            "title": "Gokaldas Exports posts Rs 15 crore Q3 profit, sees sequential recovery despite US tariff impact",
            "link": "https://economictimes.indiatimes.com/markets/stocks/earnings/gokaldas-exports-posts-rs-15-crore-q3-profit-sees-sequential-recovery-despite-us-tariff-impact/articleshow/127838054.cms",
            "description": "Gokaldas Exports posted \u20b915 crore Q3 FY26 profit, up 81% sequentially, hinting recovery despite global headwinds. Yearly profit fell on US tariffs, while productivity gains, cost controls, stable revenue, and improving margins supported quarter-on-quarter performance across India and Africa outlook.",
            "pubDate": "2026-02-01T10:23:19.470720"
        }
    ]
}