{
    "title": "RSS Feed Title",
    "link": "https://example.com",
    "description": "RSS Feed Description",
    "lastBuildDate": "2025-03-22T10:39:35.773091",
    "items": [
        {
            "title": "S&P 500 tries to avoid worst streak since 2022; Nasdaq Composite, Dow Jones near flatline",
            "link": "https://www.moneycontrol.com/news/business/markets/s-p-500-tries-to-avoid-worst-streak-since-2022-nasdaq-composite-dow-jones-near-flatline-12972189.html",
            "description": "A fifth consecutive weekly decline would mark the index\u2019s worst losing streak since 2022, underscoring the persistent unease gripping Wall Street",
            "pubDate": "2025-03-22T03:53:53.795204"
        },
        {
            "title": "Bulk Deals: Nippon India picks 28 lakh shares of TBO Tek, Norges Pension Fund sells 7 lakh Nazara Tech shares",
            "link": "https://www.moneycontrol.com/news/business/markets/bulk-deals-nippon-india-picks-28-lakh-shares-of-tbo-tek-norges-pension-fund-sells-7-lakh-nazara-tech-shares-12972173.html",
            "description": "In today's session, the market\u2019s fiery run continued, with the Nifty locking in its best weekly performance in four years, soaring 4.27 percent\u2014a feat last seen in February 2021, when it had surged 9.46 percent.",
            "pubDate": "2025-03-22T03:53:53.795291"
        },
        {
            "title": "Wall Street opens lower as trade jitters and tech weakness weigh on markets",
            "link": "https://www.moneycontrol.com/news/business/markets/wall-street-opens-lower-as-trade-jitters-and-tech-weakness-weigh-on-markets-12972130.html",
            "description": "Stocks saw a brief respite midweek after the Federal Reserve maintained its outlook for two rate cuts in 2025, but broader concerns kept risk appetite in check.",
            "pubDate": "2025-03-22T03:53:53.795371"
        },
        {
            "title": "FII net buy shares worth Rs 7,470 crore, DIIs net sellers of Rs 3,202 crore",
            "link": "https://www.moneycontrol.com/news/business/markets/fii-net-buy-shares-worth-rs-7-470-crore-diis-net-sellers-of-rs-3-202-crore-12972092.html",
            "description": "For the year so far, FIIs have been net sellers of shares worth Rs 1.57 lakh crore, while DIIs have net bought Rs 1.81 lakh crore worth of shares.",
            "pubDate": "2025-03-22T03:53:53.795444"
        },
        {
            "title": "More than 250 smallcaps post double digit return as index post biggest gain since June 2020",
            "link": "https://www.moneycontrol.com/news/business/markets/more-than-250-smallcaps-post-double-digit-return-as-index-post-biggest-gain-since-june-2020-12972296.html",
            "description": "During the week, the BSE Large-cap index added 4.6 percent, while BSE Mid-cap index rising 7 percent, posting biggest weekly gain Since February 2021 and BSE Small-cap index gaining nearly 8 percent, recording biggest gain since June 2020.",
            "pubDate": "2025-03-22T10:39:34.004959"
        },
        {
            "title": "Wall Street ends higher, dollar rises as Trump signals tariff respite",
            "link": "https://www.moneycontrol.com/news/business/markets/wall-street-ends-higher-dollar-rises-as-trump-signals-tariff-respite-12972273.html",
            "description": "The Dow Jones Industrial Average rose 31.88 points, or 0.08%, to 41,985.20, the S&P 500 rose 4.55 points, or 0.08%, to 5,667.44 and the Nasdaq Composite rose 92.43 points, or 0.52%, to 17,784.05.",
            "pubDate": "2025-03-22T10:39:34.005031"
        },
        {
            "title": "Market posts best weekly gain in 4 years; rupee appreciates",
            "link": "https://www.moneycontrol.com/news/photos/business/markets/market-posts-best-weekly-gain-in-4-years-rupee-appreciates-12972274.html",
            "description": "Indian rupee has registered a best week in over two years led by falling dollar index. During the week, the Indian rupee ended higher by 103 paise at 85.97 per dollar on March 21 against the March 13 closing of 87.",
            "pubDate": "2025-03-22T10:39:34.005097"
        }
    ]
}