{
    "title": "RSS Feed Title",
    "link": "https://example.com",
    "description": "RSS Feed Description",
    "lastBuildDate": "2025-05-07T10:18:49.985579",
    "items": [
        {
            "title": "UK-India FTA: Sectoral shake up \u2013 who gains, who loses?",
            "link": "https://www.moneycontrol.com/news/business/moneycontrol-research/uk-india-fta-sectoral-shake-up-who-gains-who-loses-13015663.html",
            "description": "Key Indian export sectors to benefit are, textiles, leather, footwear, marine products, gems & jewellery, auto parts, engineering goods, and organic chemicals.",
            "pubDate": "2025-05-07T10:18:48.353276"
        },
        {
            "title": "CEAT: Is the risk-reward turning favourable?",
            "link": "https://www.moneycontrol.com/news/business/moneycontrol-research/ceat-is-the-risk-reward-turning-favourable-13015371.html",
            "description": "Healthy volume-led growth in Q4 FY25, though margins remained under pressure due to high raw material prices.",
            "pubDate": "2025-05-07T10:18:48.353375"
        },
        {
            "title": "Himadri Specialty: Near-term growth triggers missing",
            "link": "https://www.moneycontrol.com/news/business/moneycontrol-research/himadri-specialty-near-term-growth-triggers-missing-13015397.html",
            "description": "Given the weak domestic demand for the auto sector, an unfavourable supply-demand balance is likely to show up in margins",
            "pubDate": "2025-05-07T10:18:48.353450"
        }
    ]
}