{
    "title": "RSS Feed Title",
    "link": "https://example.com",
    "description": "RSS Feed Description",
    "lastBuildDate": "2025-05-02T10:00:03.586155",
    "items": [
        {
            "title": "Buy Star Health Insurance; target of Rs 475: YES Securities",
            "link": "https://www.moneycontrol.com/news/business/stocks/buy-star-health-insurance-target-of-rs-475-yes-securities-13011437.html",
            "description": "YES Securities is bullish on Star Health Insurance has recommended buy rating on the stock with a target price of Rs 475 in its research report dated April 30, 2025.",
            "pubDate": "2025-05-02T09:59:56.684834"
        },
        {
            "title": "Buy Star Health; target of Rs 500: IIFL Securities",
            "link": "https://www.moneycontrol.com/news/business/stocks/buy-star-health-target-of-rs-500-iifl-securities-13011342.html",
            "description": "IIFL Securities is bullish on Star Health has recommended buy rating on the stock with a target price of Rs 500 in its research report dated May 01 2025.",
            "pubDate": "2025-05-02T09:59:56.684913"
        },
        {
            "title": "Banking stocks hold ground, cushion Nifty's fall; all eyes on SBI Q4 results",
            "link": "https://www.moneycontrol.com/news/business/markets/banking-stocks-hold-ground-cushion-nifty-s-fall-all-eyes-on-sbi-q4-results-13011207.html",
            "description": "Q4 results from leading private sector lenders\u2014HDFC Bank, ICICI Bank, and Axis Bank\u2014have so far received positive reactions from brokerages",
            "pubDate": "2025-05-02T09:59:56.685181"
        },
        {
            "title": "Railtel Corp shares surge 12% on strong earnings show in Q4FY25",
            "link": "https://www.moneycontrol.com/news/business/stocks/railtel-corp-shares-surge-12-on-strong-earnings-show-in-q4fy25-13011003.html",
            "description": "RailTel delivered a strong set of numbers for the March quarter, with net profit soaring 46% on-year and revenue jumping 57%.",
            "pubDate": "2025-05-02T09:59:56.685719"
        },
        {
            "title": "April auto sales impact: Maruti Suzuki, M&M, TVS Motor shares rise up to 4%",
            "link": "https://www.moneycontrol.com/news/business/markets/april-auto-sales-impact-maruti-suzuki-m-m-tvs-motor-shares-rise-up-to-4-13011023.html",
            "description": "The rise in the share prices pushed the Nifty Auto index up nearly 2 percent to hover around 22,682 in the morning trade",
            "pubDate": "2025-05-02T09:59:56.685782"
        },
        {
            "title": "Eternal Q4 FY25: Is the growth strategy losing its flavour?",
            "link": "https://www.moneycontrol.com/news/business/earnings/eternal-q4-fy25-is-the-growth-strategy-losing-its-flavour-13010923.html",
            "description": "Aggressive expansion in quick commerce hurts near-term profitability; food delivery slows, going-out app yet to deliver",
            "pubDate": "2025-05-02T09:59:56.685916"
        },
        {
            "title": "TCS, Infosys, other IT stocks surge as Cognizant lifts outlook, beats Q1 estimates",
            "link": "https://www.moneycontrol.com/news/business/markets/tcs-infosys-other-it-stocks-surge-as-cognizant-lifts-outlook-beats-q1-estimates-13011038.html",
            "description": "So far this year, Nifty IT index is down nearly 17.5 percent, but it has rebounded around 11 percent since April 9",
            "pubDate": "2025-05-02T09:59:56.686047"
        }
    ]
}