{
    "title": "RSS Feed Title",
    "link": "https://example.com",
    "description": "RSS Feed Description",
    "lastBuildDate": "2024-09-02T02:03:02.061821",
    "items": [
        {
            "title": "First Tick: Top 10 global cues for today\u00e2\u20ac\u2122s trade",
            "link": "https://www.moneycontrol.com/news/business/markets/first-tick-top-10-global-cues-for-todays-trade-27-12811317.html",
            "description": "The GIFT Nifty is  indicating a positive start for the day.",
            "pubDate": "2024-09-02T02:03:01.379040"
        }
    ]
}