{
    "title": "RSS Feed Title",
    "link": "https://example.com",
    "description": "RSS Feed Description",
    "lastBuildDate": "2024-10-16T07:26:07.211193",
    "items": [
        {
            "title": "HDFC AMC: Sector tailwinds boost Q2 earnings of this long-term compounder",
            "link": "https://www.moneycontrol.com/news/business/moneycontrol-research/hdfc-amc-sector-tailwinds-boost-q2-earnings-of-this-long-term-compounder-12843072.html",
            "description": "The premium valuation will sustain, given the sectoral tailwinds and HDFC AMC\u014c\u0106\u00d6s vantage positioning.",
            "pubDate": "2024-10-16T07:26:06.657301"
        }
    ]
}