{
    "title": "RSS Feed Title",
    "link": "https://example.com",
    "description": "RSS Feed Description",
    "lastBuildDate": "2024-12-18T03:35:17.377103",
    "items": [
        {
            "title": "Nissan and Honda consider merger to take on Toyota",
            "link": "https://www.moneycontrol.com/news/world/nissan-and-honda-consider-merger-to-take-on-toyota-12892308.html",
            "description": "A deal would effectively consolidate the Japanese auto industry into two main camps: One controlled by Honda, Nissan and Mitsubishi and another consisting of Toyota group companies",
            "pubDate": "2024-12-18T03:04:21.438887"
        },
        {
            "title": "Shriram Finance seeks record $1.25 billion offshore loan split across currencies",
            "link": "https://www.moneycontrol.com/news/business/companies/shriram-finance-seeks-record-1-25-billion-offshore-loan-split-across-currencies-12892307.html",
            "description": "The loan adds to this year\u2019s rush of offshore debt sales by Indian shadow lenders after the nation\u2019s central bank tightened rules in November 2023 that made it increasingly difficult for the sector to obtain local currency bank loans.",
            "pubDate": "2024-12-18T03:04:21.438974"
        },
        {
            "title": "Why Aadhar Housing Finance is a sound long-term bet",
            "link": "https://www.moneycontrol.com/news/business/earnings/why-aadhar-housing-finance-is-a-sound-long-term-bet-12892346.html",
            "description": "Largest affordable housing finance player, yet undervalued.",
            "pubDate": "2024-12-18T03:35:16.611412"
        }
    ]
}